RTL/APB_FSM_Controller_v2.sv
module APB_FSM_Controller(
	input        Pclk,
	input        Presetn,
	input        p_req_valid,
	input [31:0] p_req_addr,
	input [31:0] p_req_wdata,
	input        p_req_write,
	input [2:0]  p_req_sel,
	output reg   p_req_accept,
	input [31:0] Prdata,
	output reg   Pwrite,
	output reg   Penable,
	output reg [2:0] Pselx,
	output reg [31:0] Paddr,
	output reg [31:0] Pwdata,
	output reg   p_resp_valid,
	output reg [31:0] p_resp_rdata,
	output reg [1:0]  p_resp_err
);

	localparam ST_IDLE   = 2'b00;
	localparam ST_SETUP  = 2'b01;
	localparam ST_ACCESS = 2'b10;

	reg [1:0] state, next_state;
	always @(posedge Pclk or negedge Presetn) begin
		if (!Presetn) begin
			state       <= ST_IDLE;
		end else begin
			state <= next_state;
		end
	end

	always @(*) begin
		next_state = state;
		case (state)
			ST_IDLE: begin
				if (p_req_valid)
					next_state = ST_SETUP;
			end
			ST_SETUP: begin
				next_state = ST_ACCESS;
			end
			ST_ACCESS: begin
				next_state = ST_IDLE;
			end
			default: begin
				next_state = ST_IDLE;
			end
		endcase
	end

	always @(*) begin
		p_req_accept  = 1'b0;
		Pwrite        = 1'b0;
		Penable       = 1'b0;
		Pselx         = 3'b000;
		Paddr         = 32'b0;
		Pwdata        = 32'b0;
		p_resp_valid  = 1'b0;
		p_resp_rdata  = 32'b0;
		p_resp_err    = 2'b00;

		case (state)
			ST_IDLE: begin
				if (p_req_valid) begin
					p_req_accept = 1'b1;
				end
			end

			ST_SETUP: begin
				Pwrite  = p_req_write;
				Pselx   = p_req_sel;
				Paddr   = p_req_addr;
				Pwdata  = p_req_wdata;
				Penable = 1'b0;
			end

			ST_ACCESS: begin
				Pwrite  = p_req_write;
				Pselx   = p_req_sel;
				Paddr   = p_req_addr;
				Pwdata  = p_req_wdata;
				Penable = 1'b1;
				p_resp_valid = 1'b1;
				if (!p_req_write)
					p_resp_rdata = Prdata;
			end
		endcase
	end

endmodule

RTL/cdc_req_rsp_mailbox.sv
module cdc_req_rsp_mailbox #(
  parameter ADDR_W = 32,
  parameter DATA_W = 32,
  parameter SEL_W  = 3
) (
  // HCLK domain
  input                   hclk,
  input                   hresetn,
  input                   h_req_valid,
  input  [ADDR_W-1:0]     h_req_addr,
  input  [DATA_W-1:0]     h_req_wdata,
  input                   h_req_write,
  input  [SEL_W-1:0]      h_req_sel,
  output                  h_req_ready,
  output reg              h_resp_valid,
  output reg [DATA_W-1:0] h_resp_rdata,
  output reg [1:0]        h_resp_err,

  // PCLK domain
  input                   pclk,
  input                   presetn,
  output                  p_req_valid,
  output reg [ADDR_W-1:0] p_req_addr,
  output reg [DATA_W-1:0] p_req_wdata,
  output reg              p_req_write,
  output reg [SEL_W-1:0]  p_req_sel,
  input                   p_req_accept,
  input                   p_resp_valid,
  input  [DATA_W-1:0]     p_resp_rdata,
  input  [1:0]            p_resp_err
);

  // Request toggle + payload (HCLK -> PCLK)
  reg req_tgl;
  reg [ADDR_W-1:0] req_addr_reg;
  reg [DATA_W-1:0] req_wdata_reg;
  reg req_write_reg;
  reg [SEL_W-1:0]  req_sel_reg;

  // Ack toggle sync (PCLK -> HCLK)
  reg ack_tgl_sync1, ack_tgl_sync2;

  // Response toggle + payload (PCLK -> HCLK)
  reg resp_tgl;
  reg [DATA_W-1:0] resp_rdata_reg;
  reg [1:0]        resp_err_reg;

  // Response ack toggle sync (HCLK -> PCLK)
  reg resp_ack_tgl;
  reg resp_ack_sync1, resp_ack_sync2;

  // Request toggle sync (HCLK -> PCLK)
  reg req_tgl_sync1, req_tgl_sync2;
  reg req_tgl_seen;

  // Response toggle sync (PCLK -> HCLK)
  reg resp_tgl_sync1, resp_tgl_sync2;
  reg resp_tgl_seen;

  assign h_req_ready = (req_tgl == ack_tgl_sync2);

  // HCLK domain: capture request payload and toggle req_tgl
  always @(posedge hclk or negedge hresetn) begin
    if (!hresetn) begin
      req_tgl      <= 1'b0;
      req_addr_reg <= {ADDR_W{1'b0}};
      req_wdata_reg<= {DATA_W{1'b0}};
      req_write_reg<= 1'b0;
      req_sel_reg  <= {SEL_W{1'b0}};
    end else if (h_req_valid && h_req_ready) begin
      req_addr_reg <= h_req_addr;
      req_wdata_reg<= h_req_wdata;
      req_write_reg<= h_req_write;
      req_sel_reg  <= h_req_sel;
      req_tgl      <= ~req_tgl;
    end
  end

  // HCLK domain: sync ack_tgl
  always @(posedge hclk or negedge hresetn) begin
    if (!hresetn) begin
      ack_tgl_sync1 <= 1'b0;
      ack_tgl_sync2 <= 1'b0;
    end else begin
      ack_tgl_sync1 <= ack_tgl;
      ack_tgl_sync2 <= ack_tgl_sync1;
    end
  end

  // HCLK domain: sync response toggle and latch response payload
  always @(posedge hclk or negedge hresetn) begin
    if (!hresetn) begin
      resp_tgl_sync1 <= 1'b0;
      resp_tgl_sync2 <= 1'b0;
      resp_tgl_seen  <= 1'b0;
      h_resp_valid   <= 1'b0;
      h_resp_rdata   <= {DATA_W{1'b0}};
      h_resp_err     <= 2'b00;
      resp_ack_tgl   <= 1'b0;
    end else begin
      resp_tgl_sync1 <= resp_tgl;
      resp_tgl_sync2 <= resp_tgl_sync1;
      h_resp_valid   <= 1'b0;

      if (resp_tgl_sync2 != resp_tgl_seen) begin
        resp_tgl_seen <= resp_tgl_sync2;
        h_resp_rdata  <= resp_rdata_reg;
        h_resp_err    <= resp_err_reg;
        h_resp_valid  <= 1'b1;
        resp_ack_tgl  <= ~resp_ack_tgl;
      end
    end
  end

  // PCLK domain: sync req_tgl
  always @(posedge pclk or negedge presetn) begin
    if (!presetn) begin
      req_tgl_sync1 <= 1'b0;
      req_tgl_sync2 <= 1'b0;
      req_tgl_seen  <= 1'b0;
    end else begin
      req_tgl_sync1 <= req_tgl;
      req_tgl_sync2 <= req_tgl_sync1;
      if (p_req_accept && (req_tgl_sync2 != req_tgl_seen)) begin
        req_tgl_seen <= req_tgl_sync2;
      end
    end
  end

  assign p_req_valid = (req_tgl_sync2 != req_tgl_seen);

  // PCLK domain: capture payload when accepting request, then toggle ack
  reg ack_tgl;
  always @(posedge pclk or negedge presetn) begin
    if (!presetn) begin
      ack_tgl     <= 1'b0;
      p_req_addr  <= {ADDR_W{1'b0}};
      p_req_wdata <= {DATA_W{1'b0}};
      p_req_write <= 1'b0;
      p_req_sel   <= {SEL_W{1'b0}};
    end else if (p_req_accept && p_req_valid) begin
      p_req_addr  <= req_addr_reg;
      p_req_wdata <= req_wdata_reg;
      p_req_write <= req_write_reg;
      p_req_sel   <= req_sel_reg;
      ack_tgl     <= ~ack_tgl;
    end
  end

  // PCLK domain: sync resp_ack_tgl
  always @(posedge pclk or negedge presetn) begin
    if (!presetn) begin
      resp_ack_sync1 <= 1'b0;
      resp_ack_sync2 <= 1'b0;
    end else begin
      resp_ack_sync1 <= resp_ack_tgl;
      resp_ack_sync2 <= resp_ack_sync1;
    end
  end

  // PCLK domain: send response toggle when APB completes
  always @(posedge pclk or negedge presetn) begin
    if (!presetn) begin
      resp_tgl       <= 1'b0;
      resp_rdata_reg <= {DATA_W{1'b0}};
      resp_err_reg   <= 2'b00;
    end else if (p_resp_valid && (resp_tgl == resp_ack_sync2)) begin
      resp_rdata_reg <= p_resp_rdata;
      resp_err_reg   <= p_resp_err;
      resp_tgl       <= ~resp_tgl;
    end
  end

endmodule

RTL/AHB_Slave_Interface.sv

module AHB_Slave_Interface(
	input        Hclk,
	input        Hresetn,
	input        Hwrite,
	input        Hreadyin,
	input [1:0]  Htrans,
	input [31:0] Haddr,
	input [31:0] Hwdata,
	input        bridge_ready,
  output       req_valid,
	output reg [31:0] req_addr,
	output reg [31:0] req_wdata,
	output reg   req_write,
	output reg [2:0] req_sel,
  output       buffer_full
);



  reg valid_int;
  reg [2:0] tempselx;

  // Valid transfer detection
  always @(*) begin
    valid_int = 1'b0;
    if (Hresetn && Hreadyin && (Haddr >= 32'h8000_0000 && Haddr < 32'h8C00_0000) && (Htrans == 2'b10 || Htrans == 2'b11))
      valid_int = 1'b1;
  end

  // APB slave select decode from current address phase
  always @(*) begin
    tempselx = 3'b000;
    if (Hresetn && Haddr >= 32'h8000_0000 && Haddr < 32'h8400_0000)
      tempselx = 3'b001;
    else if (Hresetn && Haddr >= 32'h8400_0000 && Haddr < 32'h8800_0000)
      tempselx = 3'b010;
    else if (Hresetn && Haddr >= 32'h8800_0000 && Haddr < 32'h8C00_0000)
      tempselx = 3'b100;
  end

  reg pending_req;
  reg addr_phase;
  
  // First buffer (next)
  reg [31:0] next_addr;
  reg [31:0] next_wdata;
  reg        next_write;
  reg [2:0]  next_sel;
  reg        next_addr_phase;
  
  // Second buffer (next2) for deeper pipelining
  reg [31:0] next2_addr;
  reg [31:0] next2_wdata;
  reg        next2_write;
  reg [2:0]  next2_sel;
  reg        next2_addr_phase;
  
  wire req_fire = pending_req && bridge_ready;

  assign req_valid = req_fire;
  // Buffer is full when both next and next2 slots are occupied
  assign buffer_full = pending_req && next_addr_phase && next2_addr_phase;

  // Latch request: address phase captures addr/write/sel, data phase captures wdata
  // Support deep pipelining with 2-level buffering (next + next2)
  always @(posedge Hclk or negedge Hresetn) begin
    if (!Hresetn) begin
      req_addr        <= 32'b0;
      req_wdata       <= 32'b0;
      req_write       <= 1'b0;
      req_sel         <= 3'b000;
      pending_req     <= 1'b0;
      addr_phase      <= 1'b0;
      next_addr       <= 32'b0;
      next_wdata      <= 32'b0;
      next_write      <= 1'b0;
      next_sel        <= 3'b000;
      next_addr_phase <= 1'b0;
      next2_addr      <= 32'b0;
      next2_wdata     <= 32'b0;
      next2_write     <= 1'b0;
      next2_sel       <= 3'b000;
      next2_addr_phase<= 1'b0;
    end else begin
      // Capture data phase for current transaction
      if (addr_phase && !req_fire) begin
        req_wdata   <= Hwdata;
        pending_req <= 1'b1;
        addr_phase  <= 1'b0;
        // Check if there's a new address phase in the same cycle (pipelined)
        if (valid_int && !next_addr_phase) begin
          next_addr       <= Haddr;
          next_write      <= Hwrite;
          next_sel        <= tempselx;
          next_addr_phase <= 1'b1;
        end else if (valid_int && next_addr_phase && !next2_addr_phase) begin
          next2_addr       <= Haddr;
          next2_write      <= Hwrite;
          next2_sel        <= tempselx;
          next2_addr_phase <= 1'b1;
        end
      end
      // Capture data phase for next
      else if (next_addr_phase && !req_fire && !addr_phase && !next2_addr_phase) begin
        next_wdata <= Hwdata;
      end
      // Capture data phase for next2
      else if (next2_addr_phase && !req_fire && !addr_phase && !next_addr_phase) begin
        next2_wdata <= Hwdata;
      end
      
      // Handle firing of current pending request
      if (req_fire) begin
        pending_req <= 1'b0;
        // If we have buffered transactions, shift the pipeline
        if (next_addr_phase) begin
          // Move next to current (capture data from current Hwdata if available)
          req_addr        <= next_addr;
          req_wdata       <= Hwdata;  // Hwdata contains next's data in pipelined mode
          req_write       <= next_write;
          req_sel         <= next_sel;
          pending_req     <= 1'b1;
          addr_phase      <= 1'b0;
          
          // Move next2 to next (if exists)
          if (next2_addr_phase) begin
            next_addr       <= next2_addr;
            next_wdata      <= Hwdata;  // Can also capture next2's data if pipelined
            next_write      <= next2_write;
            next_sel        <= next2_sel;
            next_addr_phase <= 1'b1;
            next2_addr_phase<= 1'b0;
            
            // Capture new transaction into next2 if present
            if (valid_int && (Haddr != next2_addr)) begin
              next2_addr       <= Haddr;
              next2_write      <= Hwrite;
              next2_sel        <= tempselx;
              next2_addr_phase <= 1'b1;
            end
          end else begin
            // No next2, so next becomes empty
            next_addr_phase <= 1'b0;
            // Capture new transaction into next if present
            if (valid_int && (Haddr != next_addr)) begin
              next_addr       <= Haddr;
              next_write      <= Hwrite;
              next_sel        <= tempselx;
              next_addr_phase <= 1'b1;
            end
          end
        end
        // No buffered transaction, check for new one
        else if (valid_int) begin
          req_addr    <= Haddr;
          req_write   <= Hwrite;
          req_sel     <= tempselx;
          addr_phase  <= 1'b1;
        end
        else begin
          addr_phase <= 1'b0;
        end
      end
      // Capture new address phase when no pending request
      else if (!pending_req && !addr_phase && valid_int) begin
        req_addr    <= Haddr;
        req_write   <= Hwrite;
        req_sel     <= tempselx;
        addr_phase  <= 1'b1;
      end
      // Buffer into next if we're pending and see a new valid transfer
      else if (pending_req && valid_int && !next_addr_phase && !addr_phase && (Haddr != req_addr)) begin
        next_addr       <= Haddr;
        next_write      <= Hwrite;
        next_sel        <= tempselx;
        next_addr_phase <= 1'b1;
      end
      // Buffer into next2 if next is occupied
      else if (pending_req && valid_int && next_addr_phase && !next2_addr_phase && !addr_phase && (Haddr != req_addr) && (Haddr != next_addr)) begin
        next2_addr       <= Haddr;
        next2_write      <= Hwrite;
        next2_sel        <= tempselx;
        next2_addr_phase <= 1'b1;
      end
    end
  end

endmodule

RTL/Bridge_Top.sv
// Bridge Top

module Bridge_Top(
	input        Hclk,
	input        Hresetn,
	input        Pclk,
	input        Presetn,
	input        Hwrite,
	input        Hreadyin,
	input [31:0] Hwdata,
	input [31:0] Haddr,
	input [1:0]  Htrans,
	input [31:0] Prdata,
	output       Penable,
	output       Pwrite,
	output [2:0] Pselx,
	output [31:0] Paddr,
	output [31:0] Pwdata,
	output       Hreadyout,
	output [1:0] Hresp,
	output [31:0] Hrdata
);

//////////INTERMEDIATE SIGNALS
wire        h_req_valid;
wire [31:0] h_req_addr;
wire [31:0] h_req_wdata;
wire        h_req_write;
wire [2:0]  h_req_sel;
wire        h_req_ready;
wire        h_buffer_full;

wire        p_req_valid;
wire [31:0] p_req_addr;
wire [31:0] p_req_wdata;
wire        p_req_write;
wire [2:0]  p_req_sel;
wire        p_req_accept;

wire        h_resp_valid;
wire [31:0] h_resp_rdata;
wire [1:0]  h_resp_err;

wire        p_resp_valid;
wire [31:0] p_resp_rdata;
wire [1:0]  p_resp_err;

reg [31:0] Hrdata_reg;
reg [1:0]  Hresp_reg;
reg        h_pending;

//////////MODULE INSTANTIATIONS
AHB_Slave_Interface AHBSlave (
	.Hclk(Hclk),
	.Hresetn(Hresetn),
	.Hwrite(Hwrite),
	.Hreadyin(Hreadyin),
	.Htrans(Htrans),
	.Haddr(Haddr),
	.Hwdata(Hwdata),
	.bridge_ready(h_req_ready),
	.req_valid(h_req_valid),
	.req_addr(h_req_addr),
	.req_wdata(h_req_wdata),
	.req_write(h_req_write),
	.req_sel(h_req_sel),
	.buffer_full(h_buffer_full)
);

cdc_req_rsp_mailbox #(
	.ADDR_W(32),
	.DATA_W(32),
	.SEL_W(3)
) CDC (
	.hclk(Hclk),
	.hresetn(Hresetn),
	.h_req_valid(h_req_valid),
	.h_req_addr(h_req_addr),
	.h_req_wdata(h_req_wdata),
	.h_req_write(h_req_write),
	.h_req_sel(h_req_sel),
	.h_req_ready(h_req_ready),
	.h_resp_valid(h_resp_valid),
	.h_resp_rdata(h_resp_rdata),
	.h_resp_err(h_resp_err),
	.pclk(Pclk),
	.presetn(Presetn),
	.p_req_valid(p_req_valid),
	.p_req_addr(p_req_addr),
	.p_req_wdata(p_req_wdata),
	.p_req_write(p_req_write),
	.p_req_sel(p_req_sel),
	.p_req_accept(p_req_accept),
	.p_resp_valid(p_resp_valid),
	.p_resp_rdata(p_resp_rdata),
	.p_resp_err(p_resp_err)
);

APB_FSM_Controller APBControl (
	.Pclk(Pclk),
	.Presetn(Presetn),
	.p_req_valid(p_req_valid),
	.p_req_addr(p_req_addr),
	.p_req_wdata(p_req_wdata),
	.p_req_write(p_req_write),
	.p_req_sel(p_req_sel),
	.p_req_accept(p_req_accept),
	.Prdata(Prdata),
	.Pwrite(Pwrite),
	.Penable(Penable),
	.Pselx(Pselx),
	.Paddr(Paddr),
	.Pwdata(Pwdata),
	.p_resp_valid(p_resp_valid),
	.p_resp_rdata(p_resp_rdata),
	.p_resp_err(p_resp_err)
);

// HCLK domain response handling
always @(posedge Hclk or negedge Hresetn) begin
	if (!Hresetn) begin
		Hrdata_reg <= 32'b0;
		Hresp_reg  <= 2'b00;
		h_pending  <= 1'b0;
	end else begin
		if (h_req_valid && h_req_ready)
			h_pending <= 1'b1;
		if (h_resp_valid) begin
			h_pending  <= 1'b0;
			Hrdata_reg <= h_resp_rdata;
			Hresp_reg  <= h_resp_err;
		end
	end
end

assign Hrdata    = Hrdata_reg;
assign Hresp     = Hresp_reg;
assign Hreadyout = ~h_pending && ~h_buffer_full;

endmodule

tb_sanity_check.sv
`timescale 1ns/1ps

module tb_sanity_check;
  // AHB-lite signals
  reg        Hclk;
  reg        Hresetn;
  reg        Pclk;
  reg        Presetn;
  reg        Hwrite;
  reg        Hreadyin;
  reg [1:0]  Htrans;
  reg [31:0] Hwdata;
  reg [31:0] Haddr;
  reg [31:0] Prdata;

  //APB signals
  wire       Penable;
  wire       Pwrite;
  wire       Hreadyout;
  wire [1:0] Hresp;
  wire [2:0] Pselx;
  wire [31:0] Paddr;
  wire [31:0] Pwdata;
  wire [31:0] Hrdata;

  // DUT
  Bridge_Top dut (
    .Hclk(Hclk),
    .Hresetn(Hresetn),
    .Pclk(Pclk),
    .Presetn(Presetn),
    .Hwrite(Hwrite),
    .Hreadyin(Hreadyin),
    .Hreadyout(Hreadyout),
    .Hwdata(Hwdata),
    .Haddr(Haddr),
    .Htrans(Htrans),
    .Prdata(Prdata),
    .Penable(Penable),
    .Pwrite(Pwrite),
    .Pselx(Pselx),
    .Paddr(Paddr),
    .Pwdata(Pwdata),
    .Hresp(Hresp),
    .Hrdata(Hrdata)
  );

  // Clock
  always #5 Hclk = ~Hclk;
  always #10 Pclk = ~Pclk;

  initial begin
    $dumpfile("waveforms/tb_sanity_check.vcd");
    $dumpvars(0, tb_sanity_check);
  end

  initial begin
    // init
    Hclk     = 1'b0;
    Hresetn  = 1'b0;
    Pclk     = 1'b0;
    Presetn  = 1'b0;
    Hwrite   = 1'b0;
    Hreadyin = 1'b1;
    Htrans   = 2'b00;
    Hwdata   = 32'h0;
    Haddr    = 32'h0;
    Prdata   = 32'h0;

    // reset deassert
    repeat (2) @(posedge Hclk);
    #1 Hresetn = 1'b1;
    #1 Presetn = 1'b1;

    // Four AHB write transactions with proper flow control
    // Wait for Hreadyout=1 before presenting each new address phase
    
    // TRUE AHB PIPELINING:
    // Address phase of Trans(N+1) overlaps with Data phase of Trans(N)
    
    // Transaction 1 - Address Phase
    wait(Hreadyout == 1'b1);
    @(posedge Hclk);
    Hreadyin = Hreadyout;
    #1;
    Hwrite = 1'b1;
    Htrans = 2'b10; // NONSEQ
    Haddr  = 32'h8000_0004;
    $display("[%0t] TB: Trans1 addr=%h", $time, Haddr);
    
    // Transaction 1 Data + Transaction 2 Address (PIPELINED!)
    wait(Hreadyout == 1'b1);
    @(posedge Hclk);
    Hreadyin = Hreadyout;
    #1;
    Hwdata = 32'hA5A5_5A5A;
    Htrans = 2'b10; // NONSEQ for Trans2
    Haddr  = 32'h8000_0055;
    $display("[%0t] TB: Trans1 data=%h, Trans2 addr=%h", $time, Hwdata, Haddr);
    
    // Transaction 2 Data + Transaction 3 Address (PIPELINED!)
    wait(Hreadyout == 1'b1);
    @(posedge Hclk);
    Hreadyin = Hreadyout;
    #1;
    Hwdata = 32'hEAEA_EAEA;
    Htrans = 2'b10; // NONSEQ for Trans3
    Haddr  = 32'h8000_0066;
    $display("[%0t] TB: Trans2 data=%h, Trans3 addr=%h", $time, Hwdata, Haddr);
    
    // Transaction 3 Data + Transaction 4 Address (PIPELINED!)
    wait(Hreadyout == 1'b1);
    @(posedge Hclk);
    Hreadyin = Hreadyout;
    #1;
    Hwdata = 32'hBABA_BABA;
    Htrans = 2'b10; // NONSEQ for Trans4
    Haddr  = 32'h8000_0077;
    $display("[%0t] TB: Trans3 data=%h, Trans4 addr=%h", $time, Hwdata, Haddr);
    
    // Transaction 4 Data Phase (final)
    wait(Hreadyout == 1'b1);
    @(posedge Hclk);
    Hreadyin = Hreadyout;
    #1;
    Hwdata = 32'hDEAD_BEEF;
    Htrans = 2'b00; // IDLE - no more transactions
    $display("[%0t] TB: Trans4 data=%h", $time, Hwdata);

    // Haddr  = 32'h8000_0088;
    // $display("[%0t] TB: Trans5 addr=%h", $time, Haddr);

    // Wait for all to complete
    repeat (30) begin
      @(posedge Hclk);
      Hreadyin = Hreadyout;
    end
    $finish;
  end

  // Simple observation
  always @(posedge Hclk) begin
    $display("[%0t] APB sel=%b addr=%h wdata=%h en=%b | Hrdy=%b Hreadyin=%b Htrans=%b", 
             $time, Pselx, Paddr, Pwdata, Penable, Hreadyout, Hreadyin, Htrans);
  end

endmodule

waveforms/tb_sanity_check.vcd
$date
	Tue Jan 27 14:56:44 2026
$end
$version
	Icarus Verilog
$end
$timescale
	1ps
$end
$scope module tb_sanity_check $end
$var wire 1 ! Pwrite $end
$var wire 32 " Pwdata [31:0] $end
$var wire 3 # Pselx [2:0] $end
$var wire 1 $ Penable $end
$var wire 32 % Paddr [31:0] $end
$var wire 2 & Hresp [1:0] $end
$var wire 1 ' Hreadyout $end
$var wire 32 ( Hrdata [31:0] $end
$var reg 32 ) Haddr [31:0] $end
$var reg 1 * Hclk $end
$var reg 1 + Hreadyin $end
$var reg 1 , Hresetn $end
$var reg 2 - Htrans [1:0] $end
$var reg 32 . Hwdata [31:0] $end
$var reg 1 / Hwrite $end
$var reg 1 0 Pclk $end
$var reg 32 1 Prdata [31:0] $end
$var reg 1 2 Presetn $end
$scope module dut $end
$var wire 32 3 Haddr [31:0] $end
$var wire 1 * Hclk $end
$var wire 32 4 Hrdata [31:0] $end
$var wire 1 + Hreadyin $end
$var wire 1 ' Hreadyout $end
$var wire 1 , Hresetn $end
$var wire 2 5 Hresp [1:0] $end
$var wire 2 6 Htrans [1:0] $end
$var wire 32 7 Hwdata [31:0] $end
$var wire 1 / Hwrite $end
$var wire 1 0 Pclk $end
$var wire 32 8 Prdata [31:0] $end
$var wire 1 2 Presetn $end
$var wire 1 9 p_resp_valid $end
$var wire 32 : p_resp_rdata [31:0] $end
$var wire 2 ; p_resp_err [1:0] $end
$var wire 1 < p_req_write $end
$var wire 32 = p_req_wdata [31:0] $end
$var wire 1 > p_req_valid $end
$var wire 3 ? p_req_sel [2:0] $end
$var wire 32 @ p_req_addr [31:0] $end
$var wire 1 A p_req_accept $end
$var wire 1 B h_resp_valid $end
$var wire 32 C h_resp_rdata [31:0] $end
$var wire 2 D h_resp_err [1:0] $end
$var wire 1 E h_req_write $end
$var wire 32 F h_req_wdata [31:0] $end
$var wire 1 G h_req_valid $end
$var wire 3 H h_req_sel [2:0] $end
$var wire 1 I h_req_ready $end
$var wire 32 J h_req_addr [31:0] $end
$var wire 1 K h_buffer_full $end
$var wire 1 ! Pwrite $end
$var wire 32 L Pwdata [31:0] $end
$var wire 3 M Pselx [2:0] $end
$var wire 1 $ Penable $end
$var wire 32 N Paddr [31:0] $end
$var reg 32 O Hrdata_reg [31:0] $end
$var reg 2 P Hresp_reg [1:0] $end
$var reg 1 Q h_pending $end
$scope module AHBSlave $end
$var wire 32 R Haddr [31:0] $end
$var wire 1 * Hclk $end
$var wire 1 + Hreadyin $end
$var wire 1 , Hresetn $end
$var wire 2 S Htrans [1:0] $end
$var wire 32 T Hwdata [31:0] $end
$var wire 1 / Hwrite $end
$var wire 1 K buffer_full $end
$var wire 1 U req_fire $end
$var wire 1 G req_valid $end
$var wire 1 I bridge_ready $end
$var reg 1 V addr_phase $end
$var reg 32 W next2_addr [31:0] $end
$var reg 1 X next2_addr_phase $end
$var reg 3 Y next2_sel [2:0] $end
$var reg 32 Z next2_wdata [31:0] $end
$var reg 1 [ next2_write $end
$var reg 32 \ next_addr [31:0] $end
$var reg 1 ] next_addr_phase $end
$var reg 3 ^ next_sel [2:0] $end
$var reg 32 _ next_wdata [31:0] $end
$var reg 1 ` next_write $end
$var reg 1 a pending_req $end
$var reg 32 b req_addr [31:0] $end
$var reg 3 c req_sel [2:0] $end
$var reg 32 d req_wdata [31:0] $end
$var reg 1 E req_write $end
$var reg 3 e tempselx [2:0] $end
$var reg 1 f valid_int $end
$upscope $end
$scope module APBControl $end
$var wire 1 0 Pclk $end
$var wire 32 g Prdata [31:0] $end
$var wire 1 2 Presetn $end
$var wire 1 < p_req_write $end
$var wire 32 h p_req_wdata [31:0] $end
$var wire 1 > p_req_valid $end
$var wire 3 i p_req_sel [2:0] $end
$var wire 32 j p_req_addr [31:0] $end
$var parameter 2 k ST_ACCESS $end
$var parameter 2 l ST_IDLE $end
$var parameter 2 m ST_SETUP $end
$var reg 32 n Paddr [31:0] $end
$var reg 1 $ Penable $end
$var reg 3 o Pselx [2:0] $end
$var reg 32 p Pwdata [31:0] $end
$var reg 1 ! Pwrite $end
$var reg 2 q next_state [1:0] $end
$var reg 1 A p_req_accept $end
$var reg 2 r p_resp_err [1:0] $end
$var reg 32 s p_resp_rdata [31:0] $end
$var reg 1 9 p_resp_valid $end
$var reg 2 t state [1:0] $end
$upscope $end
$scope module CDC $end
$var wire 32 u h_req_addr [31:0] $end
$var wire 1 I h_req_ready $end
$var wire 3 v h_req_sel [2:0] $end
$var wire 1 G h_req_valid $end
$var wire 32 w h_req_wdata [31:0] $end
$var wire 1 E h_req_write $end
$var wire 1 * hclk $end
$var wire 1 , hresetn $end
$var wire 1 A p_req_accept $end
$var wire 1 > p_req_valid $end
$var wire 2 x p_resp_err [1:0] $end
$var wire 32 y p_resp_rdata [31:0] $end
$var wire 1 9 p_resp_valid $end
$var wire 1 0 pclk $end
$var wire 1 2 presetn $end
$var parameter 32 z ADDR_W $end
$var parameter 32 { DATA_W $end
$var parameter 32 | SEL_W $end
$var reg 1 } ack_tgl $end
$var reg 1 ~ ack_tgl_sync1 $end
$var reg 1 !" ack_tgl_sync2 $end
$var reg 2 "" h_resp_err [1:0] $end
$var reg 32 #" h_resp_rdata [31:0] $end
$var reg 1 B h_resp_valid $end
$var reg 32 $" p_req_addr [31:0] $end
$var reg 3 %" p_req_sel [2:0] $end
$var reg 32 &" p_req_wdata [31:0] $end
$var reg 1 < p_req_write $end
$var reg 32 '" req_addr_reg [31:0] $end
$var reg 3 (" req_sel_reg [2:0] $end
$var reg 1 )" req_tgl $end
$var reg 1 *" req_tgl_seen $end
$var reg 1 +" req_tgl_sync1 $end
$var reg 1 ," req_tgl_sync2 $end
$var reg 32 -" req_wdata_reg [31:0] $end
$var reg 1 ." req_write_reg $end
$var reg 1 /" resp_ack_sync1 $end
$var reg 1 0" resp_ack_sync2 $end
$var reg 1 1" resp_ack_tgl $end
$var reg 2 2" resp_err_reg [1:0] $end
$var reg 32 3" resp_rdata_reg [31:0] $end
$var reg 1 4" resp_tgl $end
$var reg 1 5" resp_tgl_seen $end
$var reg 1 6" resp_tgl_sync1 $end
$var reg 1 7" resp_tgl_sync2 $end
$upscope $end
$upscope $end
$upscope $end
$enddefinitions $end
$comment Show the parameter values. $end
$dumpall
b11 |
b100000 {
b100000 z
b1 m
b0 l
b10 k
$end
#0
$dumpvars
07"
06"
05"
04"
b0 3"
b0 2"
01"
00"
0/"
0."
b0 -"
0,"
0+"
0*"
0)"
b0 ("
b0 '"
b0 &"
b0 %"
b0 $"
b0 #"
b0 ""
0!"
0~
0}
b0 y
b0 x
b0 w
b0 v
b0 u
b0 t
b0 s
b0 r
b0 q
b0 p
b0 o
b0 n
b0 j
b0 i
b0 h
b0 g
0f
b0 e
b0 d
b0 c
b0 b
0a
0`
b0 _
b0 ^
0]
b0 \
0[
b0 Z
b0 Y
0X
b0 W
0V
0U
b0 T
b0 S
b0 R
0Q
b0 P
b0 O
b0 N
b0 M
b0 L
0K
b0 J
1I
b0 H
0G
b0 F
0E
b0 D
b0 C
0B
0A
b0 @
b0 ?
0>
b0 =
0<
b0 ;
b0 :
09
b0 8
b0 7
b0 6
b0 5
b0 4
b0 3
02
b0 1
00
0/
b0 .
b0 -
0,
1+
0*
b0 )
b0 (
1'
b0 &
b0 %
0$
b0 #
b0 "
0!
$end
#5000
1*
#10000
0*
10
#15000
1*
#16000
1,
#17000
12
#20000
0*
00
#25000
1*
#26000
b1 e
1f
b10000000000000000000000000000100 )
b10000000000000000000000000000100 3
b10000000000000000000000000000100 R
b10 -
b10 6
b10 S
1/
#30000
0*
10
#35000
1V
b1 H
b1 c
b1 v
1E
b10000000000000000000000000000100 J
b10000000000000000000000000000100 b
b10000000000000000000000000000100 u
1*
#36000
b1 e
1f
b10000000000000000000000001010101 )
b10000000000000000000000001010101 3
b10000000000000000000000001010101 R
b10100101101001010101101001011010 .
b10100101101001010101101001011010 7
b10100101101001010101101001011010 T
#40000
0*
00
#45000
1G
1U
1]
b1 ^
1`
b10000000000000000000000001010101 \
0V
1a
b10100101101001010101101001011010 F
b10100101101001010101101001011010 d
b10100101101001010101101001011010 w
1*
#46000
b1 e
1f
b10000000000000000000000001100110 )
b10000000000000000000000001100110 3
b10000000000000000000000001100110 R
b11101010111010101110101011101010 .
b11101010111010101110101011101010 7
b11101010111010101110101011101010 T
#50000
0*
10
#55000
0'
0G
0U
0I
b10000000000000000000000001100110 \
1]
b11101010111010101110101011101010 F
b11101010111010101110101011101010 d
b11101010111010101110101011101010 w
b10000000000000000000000001010101 J
b10000000000000000000000001010101 b
b10000000000000000000000001010101 u
1a
1)"
b1 ("
1."
b10100101101001010101101001011010 -"
b10000000000000000000000000000100 '"
1Q
1*
#56000
b1 e
1f
b10000000000000000000000001110111 )
b10000000000000000000000001110111 3
b10000000000000000000000001110111 R
b10111010101110101011101010111010 .
b10111010101110101011101010111010 7
b10111010101110101011101010111010 T
#60000
0*
00
#65000
1K
1X
b1 Y
1[
b10000000000000000000000001110111 W
b10111010101110101011101010111010 _
1*
#70000
1+"
0*
10
#75000
1*
#80000
0*
00
#85000
1*
#90000
1A
b1 q
1>
1,"
0*
10
#95000
1*
#100000
0*
00
#105000
1*
