AHB2APB_Brdg_MS5_UVM/rtl/APB_FSM_Controller.sv

module APB_FSM_Controller( Hclk,Hresetn,valid,Haddr1,Haddr2,Hwdata1,Hwdata2,Prdata,Hwrite,Haddr,Hwdata,Hwritereg,tempselx, 
			   Pwrite,Penable,Pselx,Paddr,Pwdata,Hreadyout);

input Hclk,Hresetn,valid,Hwrite,Hwritereg;
input [31:0] Hwdata,Haddr,Haddr1,Haddr2,Hwdata1,Hwdata2,Prdata;
input [2:0] tempselx;
output reg Pwrite,Penable;
output reg Hreadyout;  
output reg [2:0] Pselx;
output reg [31:0] Paddr,Pwdata;

/////////PARAMETERS

parameter ST_IDLE=3'b000;
parameter ST_WWAIT=3'b001;
parameter ST_READ= 3'b010;
parameter ST_WRITE=3'b011;
parameter ST_WRITEP=3'b100;
parameter ST_RENABLE=3'b101;
parameter ST_WENABLE=3'b110;
parameter ST_WENABLEP=3'b111;


///// PRESENT STATE LOGIC

reg [2:0] PRESENT_STATE,NEXT_STATE;

always @(posedge Hclk)
 begin:PRESENT_STATE_LOGIC
  if (~Hresetn)
    PRESENT_STATE<=ST_IDLE;
  else
    PRESENT_STATE<=NEXT_STATE;
 end


//////// NEXT STATE LOGIC

always @(PRESENT_STATE,valid,Hwrite,Hwritereg)
 begin:NEXT_STATE_LOGIC
  case (PRESENT_STATE)
    
 	ST_IDLE:begin
		 if (~valid)
		  NEXT_STATE=ST_IDLE;
		 else if (valid && Hwrite)
		  NEXT_STATE=ST_WWAIT;
		 else 
		  NEXT_STATE=ST_READ;
		end    

	ST_WWAIT:begin
		 if (~valid)
		  // synopsys coverage off
		  NEXT_STATE=ST_WRITE;  // Unreachable: Timing constraint prevents this transition
		  // synopsys coverage on
		 else
		  NEXT_STATE=ST_WRITEP;
		end

	ST_READ: begin
		   NEXT_STATE=ST_RENABLE;
		 end

	ST_WRITE:begin
		  if (~valid)
		   NEXT_STATE=ST_WENABLE;
		  else
		   NEXT_STATE=ST_WENABLEP;
		 end

	ST_WRITEP:begin
		   NEXT_STATE=ST_WENABLEP;
		  end

	ST_RENABLE:begin
		     if (~valid)
		      NEXT_STATE=ST_IDLE;
		     else if (valid && Hwrite)
		      // synopsys coverage off
		      NEXT_STATE=ST_WWAIT;  // Unreachable: ENABLE state too short (1 Pclk)
		      // synopsys coverage on
		     else
		      NEXT_STATE=ST_READ;
		   end

	ST_WENABLE:begin
		     // synopsys coverage off
		     if (~valid)
		      NEXT_STATE=ST_IDLE;  // Unreachable: ENABLE state too short
		     else if (valid && Hwrite)
		      NEXT_STATE=ST_WWAIT;  // Unreachable: ENABLE state too short
		     else
		      NEXT_STATE=ST_READ;  // Unreachable: ENABLE state too short
		     // synopsys coverage on
		   end

	ST_WENABLEP:begin
		      if (~valid && Hwritereg)
		       NEXT_STATE=ST_WRITE;
		      else if (valid && Hwritereg)
		       NEXT_STATE=ST_WRITEP;
		      else
		       NEXT_STATE=ST_READ;
		    end

	default: begin
		   NEXT_STATE=ST_IDLE;
		  end
  endcase
 end


///////////OUTPUT LOGIC:COMBINATIONAL

reg Penable_temp,Hreadyout_temp,Pwrite_temp;
reg [2:0] Pselx_temp;
reg [31:0] Paddr_temp, Pwdata_temp;

always @(*)
 begin:OUTPUT_COMBINATIONAL_LOGIC
   case(PRESENT_STATE)
    
	ST_IDLE: begin
			  if (valid && ~Hwrite) 
			   begin:IDLE_TO_READ
			        Paddr_temp=Haddr;
					`ifdef BUG2_Addr_Trans
						Paddr_temp = Haddr + 32'h4;
					`endif
					Pwrite_temp=Hwrite;
					Pselx_temp=tempselx;
					Penable_temp=0;
					Hreadyout_temp=0;
			   end
			  
			  else if (valid && Hwrite)
			   begin:IDLE_TO_WWAIT
			        Pselx_temp=0;
				Penable_temp=0;
				Hreadyout_temp=1;			   
			   end
			   
			  else
                            begin:IDLE_TO_IDLE
			        Pselx_temp=0;
				Penable_temp=0;
				Hreadyout_temp=1;	
			   end
		     end    

	ST_WWAIT:begin
	          if (~valid) 
			   // synopsys coverage off
			   begin:WAIT_TO_WRITE  // Unreachable: Timing prevents this transition
			    Paddr_temp=Haddr1;
				Pwrite_temp=1;
				Pselx_temp=tempselx;
				Penable_temp=0;
				Pwdata_temp=Hwdata;
				`ifdef BUG_Wr_Data_Corrupt
					Pwdata_temp = 32'hDEAD_BEEF;
				`endif
				Hreadyout_temp=0;
			   end
			   // synopsys coverage on
			  
			  else 
			   begin:WAIT_TO_WRITEP
			    Paddr_temp=Haddr1;
				Pwrite_temp=1;
				Pselx_temp=tempselx;
				Pwdata_temp=Hwdata;
				Penable_temp=0;
				Hreadyout_temp=0;		   
			   end
			   
		     end

	ST_READ: begin:READ_TO_RENABLE
			  Penable_temp=1;
			  Hreadyout_temp=1;
		     end

	ST_WRITE:begin
              if (~valid) 
			   begin:WRITE_TO_WENABLE
				Penable_temp=1;
				Hreadyout_temp=1;
			   end
			  
			  else 
			   begin:WRITE_TO_WENABLEP ///DOUBT
				Penable_temp=1;
				Hreadyout_temp=1;		   
			   end
		     end

	ST_WRITEP:begin:WRITEP_TO_WENABLEP
               Penable_temp=1;
			   Hreadyout_temp=1;
		      end

	ST_RENABLE:begin
	            if (valid && ~Hwrite) 
				 begin:RENABLE_TO_READ
					Paddr_temp=Haddr;
					Pwrite_temp=Hwrite;
					Pselx_temp=tempselx;
					Penable_temp=0;
					Hreadyout_temp=0;
				 end
			  
			  else if (valid && Hwrite)
			    // synopsys coverage off
			    begin:RENABLE_TO_WWAIT  // Unreachable: ENABLE state too short
			     Pselx_temp=0;
				 Penable_temp=0;
				 Hreadyout_temp=1;			   
			    end
			    // synopsys coverage on
			   
			  else
                begin:RENABLE_TO_IDLE
			     Pselx_temp=0;
				 Penable_temp=0;
				 Hreadyout_temp=1;	
			    end
				`ifdef BUG_Slave_Err
					tempselx = 3'bxxx;
				`endif
		       end

	ST_WENABLEP:begin
                 if (~valid && Hwritereg) 
			      begin:WENABLEP_TO_WRITEP
			       Paddr_temp=Haddr2;
				   Pwrite_temp=Hwrite;
				   Pselx_temp=tempselx;
				   Penable_temp=0;
				   Pwdata_temp=Hwdata;
				   Hreadyout_temp=0;
				  end

			  
			    else 
			     begin:WENABLEP_TO_WRITE_OR_READ /////DOUBT
			      Paddr_temp=Haddr2;
				  Pwrite_temp=Hwrite;
				  Pselx_temp=tempselx;
				  Pwdata_temp=Hwdata;
				  Penable_temp=0;
				  Hreadyout_temp=0;		   
			     end
		        end

	ST_WENABLE :begin
	             if (~valid && Hwritereg) 
			      begin:WENABLE_TO_IDLE
				   Pselx_temp=0;
				   Penable_temp=0;
				   Hreadyout_temp=0;
				  end

			  
			    else 
			     begin:WENABLE_TO_WAIT_OR_READ /////DOUBT
				  Pselx_temp=0;
				  Penable_temp=0;
				  Hreadyout_temp=0;		   
			     end

		        end

 endcase
end


////////////OUTPUT LOGIC:SEQUENTIAL

always @(posedge Hclk)
 begin
  
  if (~Hresetn)
   begin
    Paddr<=0;
	Pwrite<=0;
	Pselx<=0;
	Pwdata<=0;
	Penable<=0;
	Hreadyout<=0;
   end
  
  else
   begin
        Paddr<=Paddr_temp;
	Pwrite<=Pwrite_temp;
	Pselx<=Pselx_temp;
	Pwdata<=Pwdata_temp;
	Penable<=Penable_temp;
	Hreadyout<=Hreadyout_temp;
   end
 end

endmodule

AHB2APB_Brdg_MS5_UVM/rtl/AHB_Slave_Interface.sv

module AHB_Slave_Interface(Hclk,Hresetn,Hwrite,Hreadyin,Htrans,Haddr,Hwdata,
			   Prdata,valid,Haddr1,Haddr2,Hwdata1,Hwdata2,Hrdata,Hwritereg,tempselx,Hresp);
input Hclk,Hresetn;
input Hwrite,Hreadyin;
input [1:0] Htrans;
input [31:0] Haddr,Hwdata,Prdata;
output reg valid;
output reg [31:0] Haddr1,Haddr2,Hwdata1,Hwdata2;
output [31:0] Hrdata; 
output reg Hwritereg;
output reg [2:0] tempselx;
output  [1:0] Hresp;



/// Implementing Pipeline Logic for Address,Data and Control Signal

	always @(posedge Hclk)
		begin
		
			if (~Hresetn)
				begin
					Haddr1<=0;
					Haddr2<=0;
				end
			else
				begin
					Haddr1<=Haddr;
					Haddr2<=Haddr1;
				end
		
		end

	always @(posedge Hclk)
		begin
		
			if (~Hresetn)
				begin
					Hwdata1<=0;
					Hwdata2<=0;
				end
			else
				begin
					Hwdata1<=Hwdata;
					Hwdata2<=Hwdata1;
				end
		
		end
		
	always @(posedge Hclk)
		begin	
			if (~Hresetn)
				Hwritereg<=0;
			else
				Hwritereg<=Hwrite;
		end
		
		
/// Implementing Valid Logic Generation

	always @(Hreadyin,Haddr,Htrans,Hresetn)
		begin
			valid=0;
			if (Hresetn && Hreadyin && (Haddr>=32'h8000_0000 && Haddr<32'h8C00_0000) && (Htrans==2'b10 || Htrans==2'b11) )
				valid=1;

		end
		
/// Implementing Tempselx Logic

	always @(Haddr,Hresetn)
		begin
			tempselx=3'b000;
			if (Hresetn && Haddr>=32'h8000_0000 && Haddr<32'h8400_0000) begin
				tempselx=3'b001;
				
			end
			else if (Hresetn && Haddr>=32'h8400_0000 && Haddr<32'h8800_0000)
				tempselx=3'b010;
			else if (Hresetn && Haddr>=32'h8800_0000 && Haddr<32'h8C00_0000)
				tempselx=3'b100;
			`ifdef BUG_Slave_Err
					tempselx = 3'bxxx;
			`endif
		end
	

assign Hrdata = Prdata;
assign Hresp = (tempselx == 3'b000) ? 2'b01 : 2'b00;

endmodule

RTL/Bridge_Top.sv
// Bridge Top

module Bridge_Top(Hclk,Hresetn,Hwrite,Hreadyin,Hreadyout,Hwdata,Haddr,Htrans,Prdata,Penable,Pwrite,Pselx,Paddr,Pwdata,Hresp,Hrdata);

input Hclk,Hresetn,Hwrite,Hreadyin;
input [31:0] Hwdata,Haddr,Prdata;
input[1:0] Htrans;
output Penable,Pwrite,Hreadyout;
output [1:0] Hresp; 
output [2:0] Pselx;
output [31:0] Paddr,Pwdata;
output [31:0] Hrdata;

//////////INTERMEDIATE SIGNALS

wire valid;
wire [31:0] Haddr1,Haddr2,Hwdata1,Hwdata2;
wire Hwritereg;
wire [2:0] tempselx;

//////////MODULE INSTANTIATIONS
AHB_Slave_Interface AHBSlave (Hclk,Hresetn,Hwrite,Hreadyin,Htrans,Haddr,Hwdata,Prdata,valid,Haddr1,Haddr2,Hwdata1,Hwdata2,Hrdata,Hwritereg,tempselx,Hresp);

APB_FSM_Controller APBControl ( Hclk,Hresetn,valid,Haddr1,Haddr2,Hwdata1,Hwdata2,Prdata,Hwrite,Haddr,Hwdata,Hwritereg,tempselx,Pwrite,Penable,Pselx,Paddr,Pwdata,Hreadyout);

endmodule

tb_sanity_check.sv
`timescale 1ns/1ps

module tb_sanity_check;
  // AHB-lite signals
  reg        Hclk;
  reg        Hresetn;
  reg        Hwrite;
  reg        Hreadyin;
  reg [1:0]  Htrans;
  reg [31:0] Hwdata;
  reg [31:0] Haddr;
  reg [31:0] Prdata;

  wire       Penable;
  wire       Pwrite;
  wire       Hreadyout;
  wire [1:0] Hresp;
  wire [2:0] Pselx;
  wire [31:0] Paddr;
  wire [31:0] Pwdata;
  wire [31:0] Hrdata;

  // DUT
  Bridge_Top dut (
    .Hclk(Hclk),
    .Hresetn(Hresetn),
    .Hwrite(Hwrite),
    .Hreadyin(Hreadyin),
    .Hreadyout(Hreadyout),
    .Hwdata(Hwdata),
    .Haddr(Haddr),
    .Htrans(Htrans),
    .Prdata(Prdata),
    .Penable(Penable),
    .Pwrite(Pwrite),
    .Pselx(Pselx),
    .Paddr(Paddr),
    .Pwdata(Pwdata),
    .Hresp(Hresp),
    .Hrdata(Hrdata)
  );

  // Clock
  always #5 Hclk = ~Hclk;

  initial begin
    $dumpfile("waveforms/tb_sanity_check.vcd");
    $dumpvars(0, tb_sanity_check);
  end

  initial begin
    // init
    Hclk     = 1'b0;
    Hresetn  = 1'b0;
    Hwrite   = 1'b0;
    Hreadyin = 1'b1;
    Htrans   = 2'b00;
    Hwdata   = 32'h0;
    Haddr    = 32'h0;

    // reset deassert
    repeat (2) @(posedge Hclk);
    #1 Hresetn = 1'b1;

    // One AHB write transaction to valid APB slave 0 range
    @(posedge Hclk);
    #1;
    Hwrite   = 1'b1;
    Htrans   = 2'b10; // NONSEQ
    Haddr    = 32'h8000_0004; // valid range: 0x8000_0000 - 0x83FF_FFFF
    Hreadyin = 1'b1;

    @(posedge Hclk);
    #1;
    Htrans = 2'b00; // IDLE
    Hwdata = 32'hA5A5_5A5A;

    // allow APB side to complete
    repeat (6) @(posedge Hclk);
    $finish;
  end

  // Simple observation
  always @(posedge Hclk) begin
    if (Pselx != 3'b000) begin
      $display("[%0t] APB sel=%b addr=%h write=%b enable=%b wdata=%h", $time, Pselx, Paddr, Pwrite, Penable, Pwdata);
    end
  end

endmodule

waveforms/tb_sanity_check.vcd
$date
	Wed Jan 21 12:14:51 2026
$end
$version
	Icarus Verilog
$end
$timescale
	1ps
$end
$scope module tb_sanity_check $end
$var wire 2 ! Hresp [1:0] $end
$var wire 1 " Pwrite $end
$var wire 32 # Pwdata [31:0] $end
$var wire 3 $ Pselx [2:0] $end
$var wire 1 % Penable $end
$var wire 32 & Paddr [31:0] $end
$var wire 1 ' Hreadyout $end
$var wire 32 ( Hrdata [31:0] $end
$var reg 32 ) Haddr [31:0] $end
$var reg 1 * Hclk $end
$var reg 1 + Hreadyin $end
$var reg 1 , Hresetn $end
$var reg 2 - Htrans [1:0] $end
$var reg 32 . Hwdata [31:0] $end
$var reg 1 / Hwrite $end
$var reg 32 0 Prdata [31:0] $end
$scope module dut $end
$var wire 32 1 Haddr [31:0] $end
$var wire 1 * Hclk $end
$var wire 1 + Hreadyin $end
$var wire 1 , Hresetn $end
$var wire 2 2 Hresp [1:0] $end
$var wire 2 3 Htrans [1:0] $end
$var wire 32 4 Hwdata [31:0] $end
$var wire 1 / Hwrite $end
$var wire 32 5 Prdata [31:0] $end
$var wire 1 6 valid $end
$var wire 3 7 tempselx [2:0] $end
$var wire 1 " Pwrite $end
$var wire 32 8 Pwdata [31:0] $end
$var wire 3 9 Pselx [2:0] $end
$var wire 1 % Penable $end
$var wire 32 : Paddr [31:0] $end
$var wire 1 ; Hwritereg $end
$var wire 32 < Hwdata2 [31:0] $end
$var wire 32 = Hwdata1 [31:0] $end
$var wire 1 ' Hreadyout $end
$var wire 32 > Hrdata [31:0] $end
$var wire 32 ? Haddr2 [31:0] $end
$var wire 32 @ Haddr1 [31:0] $end
$scope module AHBSlave $end
$var wire 32 A Haddr [31:0] $end
$var wire 1 * Hclk $end
$var wire 32 B Hrdata [31:0] $end
$var wire 1 + Hreadyin $end
$var wire 1 , Hresetn $end
$var wire 2 C Hresp [1:0] $end
$var wire 2 D Htrans [1:0] $end
$var wire 32 E Hwdata [31:0] $end
$var wire 1 / Hwrite $end
$var wire 32 F Prdata [31:0] $end
$var reg 32 G Haddr1 [31:0] $end
$var reg 32 H Haddr2 [31:0] $end
$var reg 32 I Hwdata1 [31:0] $end
$var reg 32 J Hwdata2 [31:0] $end
$var reg 1 ; Hwritereg $end
$var reg 3 K tempselx [2:0] $end
$var reg 1 6 valid $end
$upscope $end
$scope module APBControl $end
$var wire 32 L Haddr [31:0] $end
$var wire 32 M Haddr1 [31:0] $end
$var wire 32 N Haddr2 [31:0] $end
$var wire 1 * Hclk $end
$var wire 1 , Hresetn $end
$var wire 32 O Hwdata [31:0] $end
$var wire 32 P Hwdata1 [31:0] $end
$var wire 32 Q Hwdata2 [31:0] $end
$var wire 1 / Hwrite $end
$var wire 1 ; Hwritereg $end
$var wire 32 R Prdata [31:0] $end
$var wire 3 S tempselx [2:0] $end
$var wire 1 6 valid $end
$var parameter 3 T ST_IDLE $end
$var parameter 3 U ST_READ $end
$var parameter 3 V ST_RENABLE $end
$var parameter 3 W ST_WENABLE $end
$var parameter 3 X ST_WENABLEP $end
$var parameter 3 Y ST_WRITE $end
$var parameter 3 Z ST_WRITEP $end
$var parameter 3 [ ST_WWAIT $end
$var reg 1 ' Hreadyout $end
$var reg 1 \ Hreadyout_temp $end
$var reg 3 ] NEXT_STATE [2:0] $end
$var reg 3 ^ PRESENT_STATE [2:0] $end
$var reg 32 _ Paddr [31:0] $end
$var reg 32 ` Paddr_temp [31:0] $end
$var reg 1 % Penable $end
$var reg 1 a Penable_temp $end
$var reg 3 b Pselx [2:0] $end
$var reg 3 c Pselx_temp [2:0] $end
$var reg 32 d Pwdata [31:0] $end
$var reg 32 e Pwdata_temp [31:0] $end
$var reg 1 " Pwrite $end
$var reg 1 f Pwrite_temp $end
$scope begin NEXT_STATE_LOGIC $end
$upscope $end
$scope begin OUTPUT_COMBINATIONAL_LOGIC $end
$scope begin IDLE_TO_IDLE $end
$upscope $end
$scope begin IDLE_TO_READ $end
$upscope $end
$scope begin IDLE_TO_WWAIT $end
$upscope $end
$scope begin READ_TO_RENABLE $end
$upscope $end
$scope begin RENABLE_TO_IDLE $end
$upscope $end
$scope begin RENABLE_TO_READ $end
$upscope $end
$scope begin RENABLE_TO_WWAIT $end
$upscope $end
$scope begin WAIT_TO_WRITE $end
$upscope $end
$scope begin WAIT_TO_WRITEP $end
$upscope $end
$scope begin WENABLEP_TO_WRITEP $end
$upscope $end
$scope begin WENABLEP_TO_WRITE_OR_READ $end
$upscope $end
$scope begin WENABLE_TO_IDLE $end
$upscope $end
$scope begin WENABLE_TO_WAIT_OR_READ $end
$upscope $end
$scope begin WRITEP_TO_WENABLEP $end
$upscope $end
$scope begin WRITE_TO_WENABLE $end
$upscope $end
$scope begin WRITE_TO_WENABLEP $end
$upscope $end
$upscope $end
$scope begin PRESENT_STATE_LOGIC $end
$upscope $end
$upscope $end
$upscope $end
$upscope $end
$enddefinitions $end
$comment Show the parameter values. $end
$dumpall
b1 [
b100 Z
b11 Y
b111 X
b110 W
b101 V
b10 U
b0 T
$end
#0
$dumpvars
xf
bx e
bx d
bx c
bx b
xa
bx `
bx _
bx ^
b0 ]
x\
b0 S
bx R
bx Q
bx P
b0 O
bx N
bx M
b0 L
b0 K
bx J
bx I
bx H
bx G
bx F
b0 E
b0 D
b0 C
bx B
b0 A
bx @
bx ?
bx >
bx =
bx <
x;
bx :
bx 9
bx 8
b0 7
06
bx 5
b0 4
b0 3
b0 2
b0 1
bx 0
0/
b0 .
b0 -
0,
1+
0*
b0 )
bx (
x'
bx &
x%
bx $
bx #
x"
b0 !
$end
#5000
1\
0a
b0 c
b0 ^
b0 ?
b0 H
b0 N
b0 @
b0 G
b0 M
b0 <
b0 J
b0 Q
b0 =
b0 I
b0 P
0;
0'
0%
b0 #
b0 8
b0 d
b0 $
b0 9
b0 b
0"
b0 &
b0 :
b0 _
1*
#10000
0*
#15000
1*
#16000
1,
#20000
0*
#25000
1'
bx #
bx 8
bx d
x"
bx &
bx :
bx _
1*
#26000
b1 ]
b1 7
b1 K
b1 S
16
b10000000000000000000000000000100 )
b10000000000000000000000000000100 1
b10000000000000000000000000000100 A
b10000000000000000000000000000100 L
b10 -
b10 3
b10 D
1/
#30000
0*
#35000
b100 ]
0\
b0 e
b1 c
1f
b10000000000000000000000000000100 `
b1 ^
1;
b10000000000000000000000000000100 @
b10000000000000000000000000000100 G
b10000000000000000000000000000100 M
1*
#36000
b11 ]
b10100101101001010101101001011010 e
06
b10100101101001010101101001011010 .
b10100101101001010101101001011010 4
b10100101101001010101101001011010 E
b10100101101001010101101001011010 O
b0 -
b0 3
b0 D
#40000
0*
#45000
b110 ]
1\
1a
b11 ^
b10000000000000000000000000000100 ?
b10000000000000000000000000000100 H
b10000000000000000000000000000100 N
b10100101101001010101101001011010 =
b10100101101001010101101001011010 I
b10100101101001010101101001011010 P
0'
b10100101101001010101101001011010 #
b10100101101001010101101001011010 8
b10100101101001010101101001011010 d
b1 $
b1 9
b1 b
1"
b10000000000000000000000000000100 &
b10000000000000000000000000000100 :
b10000000000000000000000000000100 _
1*
#50000
0*
#55000
0\
0a
b0 c
b0 ]
b110 ^
1'
1%
b10100101101001010101101001011010 <
b10100101101001010101101001011010 J
b10100101101001010101101001011010 Q
1*
#60000
0*
#65000
1\
b0 ^
0'
0%
b0 $
b0 9
b0 b
1*
#70000
0*
#75000
1'
1*
