RTL/CDC_Handler.sv

module CDC_Handler(
    // Clock and Reset
    input Hclk, Pclk, Hresetn,
    
    // APB outputs from FSM (HCLK domain)
    input Penable_hclk, Pwrite_hclk,
    input [2:0] Pselx_hclk,
    input [31:0] Paddr_hclk, Pwdata_hclk,
    
    // APB outputs to APB bus (PCLK domain)
    output Penable_pclk, Pwrite_pclk,
    output [2:0] Pselx_pclk,
    output [31:0] Paddr_pclk, Pwdata_pclk,
    
    // APB input from APB bus (PCLK domain)
    input [31:0] Prdata_pclk,
    
    // APB input to AHB side (HCLK domain)
    output [31:0] Prdata_hclk
);

// 2-FF Synchronizers: HCLK -> PCLK (APB control/data signals)
reg Penable_sync1, Penable_sync2;
reg Pwrite_sync1, Pwrite_sync2;
reg [2:0] Pselx_sync1, Pselx_sync2;
reg [31:0] Paddr_sync1, Paddr_sync2;
reg [31:0] Pwdata_sync1, Pwdata_sync2;

// 2-FF Synchronizer: PCLK -> HCLK (Prdata)
reg [31:0] Prdata_sync1, Prdata_sync2;

// HCLK to PCLK synchronizers (APB outputs)
always @(posedge Pclk) begin
    if (~Hresetn) begin
        // First stage
        Penable_sync1 <= 0;
        Pwrite_sync1 <= 0;
        Pselx_sync1 <= 0;
        Paddr_sync1 <= 0;
        Pwdata_sync1 <= 0;
        
        // Second stage
        Penable_sync2 <= 0;
        Pwrite_sync2 <= 0;
        Pselx_sync2 <= 0;
        Paddr_sync2 <= 0;
        Pwdata_sync2 <= 0;
    end
    else begin
        // First stage
        Penable_sync1 <= Penable_hclk;
        Pwrite_sync1 <= Pwrite_hclk;
        Pselx_sync1 <= Pselx_hclk;
        Paddr_sync1 <= Paddr_hclk;
        Pwdata_sync1 <= Pwdata_hclk;
        
        // Second stage
        Penable_sync2 <= Penable_sync1;
        Pwrite_sync2 <= Pwrite_sync1;
        Pselx_sync2 <= Pselx_sync1;
        Paddr_sync2 <= Paddr_sync1;
        Pwdata_sync2 <= Pwdata_sync1;
    end
end

// Output to PCLK domain (APB bus)
assign Penable_pclk = Penable_sync2;
assign Pwrite_pclk = Pwrite_sync2;
assign Pselx_pclk = Pselx_sync2;
assign Paddr_pclk = Paddr_sync2;
assign Pwdata_pclk = Pwdata_sync2;

// PCLK to HCLK synchronizer (Prdata from APB)
always @(posedge Hclk) begin
    if (~Hresetn) begin
        Prdata_sync1 <= 0;
        Prdata_sync2 <= 0;
    end
    else begin
        Prdata_sync1 <= Prdata_pclk;
        Prdata_sync2 <= Prdata_sync1;
    end
end

// Output to HCLK domain
assign Prdata_hclk = Prdata_sync2;

endmodule

AHB2APB_Brdg_MS2_Class/rtl/APB_FSM_Controller.sv

module APB_FSM_Controller( Hclk,Hresetn,valid,Haddr1,Haddr2,Hwdata1,Hwdata2,Prdata,Hwrite,Haddr,Hwdata,Hwritereg,tempselx, 
			   Pwrite,Penable,Pselx,Paddr,Pwdata,Hreadyout);

input Hclk,Hresetn,valid,Hwrite,Hwritereg;
input [31:0] Hwdata,Haddr,Haddr1,Haddr2,Hwdata1,Hwdata2,Prdata;
input [2:0] tempselx;
output reg Pwrite,Penable;
output reg Hreadyout;  
output reg [2:0] Pselx;
output reg [31:0] Paddr,Pwdata;

/////////PARAMETERS

parameter ST_IDLE=3'b000;
parameter ST_WWAIT=3'b001;
parameter ST_READ= 3'b010;
parameter ST_WRITE=3'b011;
parameter ST_WRITEP=3'b100;
parameter ST_RENABLE=3'b101;
parameter ST_WENABLE=3'b110;
parameter ST_WENABLEP=3'b111;


///// PRESENT STATE LOGIC

reg [2:0] PRESENT_STATE,NEXT_STATE;

always @(posedge Hclk)
 begin:PRESENT_STATE_LOGIC
  if (~Hresetn)
    PRESENT_STATE<=ST_IDLE;
  else
    PRESENT_STATE<=NEXT_STATE;
 end


//////// NEXT STATE LOGIC

always @(PRESENT_STATE,valid,Hwrite,Hwritereg)
 begin:NEXT_STATE_LOGIC
  case (PRESENT_STATE)
    
 	ST_IDLE:begin
		 if (~valid)
		  NEXT_STATE=ST_IDLE;
		 else if (valid && Hwrite)
		  NEXT_STATE=ST_WWAIT;
		 else 
		  NEXT_STATE=ST_READ;
		end    

	ST_WWAIT:begin
		 if (~valid)
		  NEXT_STATE=ST_WRITE;
		 else
		  NEXT_STATE=ST_WRITEP;
		end

	ST_READ: begin
		   NEXT_STATE=ST_RENABLE;
		 end

	ST_WRITE:begin
		  if (~valid)
		   NEXT_STATE=ST_WENABLE;
		  else
		   NEXT_STATE=ST_WENABLEP;
		 end

	ST_WRITEP:begin
		   NEXT_STATE=ST_WENABLEP;
		  end

	ST_RENABLE:begin
		     if (~valid)
		      NEXT_STATE=ST_IDLE;
		     else if (valid && Hwrite)
		      NEXT_STATE=ST_WWAIT;
		     else
		      NEXT_STATE=ST_READ;
		   end

	ST_WENABLE:begin
		     if (~valid)
		      NEXT_STATE=ST_IDLE;
		     else if (valid && Hwrite)
		      NEXT_STATE=ST_WWAIT;
		     else
		      NEXT_STATE=ST_READ;
		   end

	ST_WENABLEP:begin
		      if (~valid && Hwritereg)
		       NEXT_STATE=ST_WRITE;
		      else if (valid && Hwritereg)
		       NEXT_STATE=ST_WRITEP;
		      else
		       NEXT_STATE=ST_READ;
		    end

	default: begin
		   NEXT_STATE=ST_IDLE;
		  end
  endcase
 end


///////////OUTPUT LOGIC:COMBINATIONAL

reg Penable_temp,Hreadyout_temp,Pwrite_temp;
reg [2:0] Pselx_temp;
reg [31:0] Paddr_temp, Pwdata_temp;

always @(*)
 begin:OUTPUT_COMBINATIONAL_LOGIC
   case(PRESENT_STATE)
    
	ST_IDLE: begin
			  if (valid && ~Hwrite) 
			   begin:IDLE_TO_READ
			        Paddr_temp=Haddr;
				Pwrite_temp=Hwrite;
				Pselx_temp=tempselx;
				Penable_temp=0;
				Hreadyout_temp=0;
			   end
			  
			  else if (valid && Hwrite)
			   begin:IDLE_TO_WWAIT
			        Pselx_temp=0;
				Penable_temp=0;
				Hreadyout_temp=1;			   
			   end
			   
			  else
                            begin:IDLE_TO_IDLE
			        Pselx_temp=0;
				Penable_temp=0;
				Hreadyout_temp=1;	
			   end
		     end    

	ST_WWAIT:begin
	          if (~valid) 
			   begin:WAIT_TO_WRITE
			    Paddr_temp=Haddr1;
				Pwrite_temp=1;
				Pselx_temp=tempselx;
				Penable_temp=0;
				Pwdata_temp=Hwdata;
				Hreadyout_temp=0;
			   end
			  
			  else 
			   begin:WAIT_TO_WRITEP
			    Paddr_temp=Haddr1;
				Pwrite_temp=1;
				Pselx_temp=tempselx;
				Pwdata_temp=Hwdata;
				Penable_temp=0;
				Hreadyout_temp=0;		   
			   end
			   
		     end  

	ST_READ: begin:READ_TO_RENABLE
			  Penable_temp=1;
			  Hreadyout_temp=1;
		     end

	ST_WRITE:begin
              if (~valid) 
			   begin:WRITE_TO_WENABLE
				Penable_temp=1;
				Hreadyout_temp=1;
			   end
			  
			  else 
			   begin:WRITE_TO_WENABLEP ///DOUBT
				Penable_temp=1;
				Hreadyout_temp=1;		   
			   end
		     end

	ST_WRITEP:begin:WRITEP_TO_WENABLEP
               Penable_temp=1;
			   Hreadyout_temp=1;
		      end

	ST_RENABLE:begin
	            if (valid && ~Hwrite) 
				 begin:RENABLE_TO_READ
					Paddr_temp=Haddr;
					Pwrite_temp=Hwrite;
					Pselx_temp=tempselx;
					Penable_temp=0;
					Hreadyout_temp=0;
				 end
			  
			  else if (valid && Hwrite)
			    begin:RENABLE_TO_WWAIT
			     Pselx_temp=0;
				 Penable_temp=0;
				 Hreadyout_temp=1;			   
			    end
			   
			  else
                begin:RENABLE_TO_IDLE
			     Pselx_temp=0;
				 Penable_temp=0;
				 Hreadyout_temp=1;	
			    end

		       end

	ST_WENABLEP:begin
                 if (~valid && Hwritereg) 
			      begin:WENABLEP_TO_WRITEP
			       Paddr_temp=Haddr2;
				   Pwrite_temp=Hwrite;
				   Pselx_temp=tempselx;
				   Penable_temp=0;
				   Pwdata_temp=Hwdata;
				   Hreadyout_temp=0;
				  end

			  
			    else 
			     begin:WENABLEP_TO_WRITE_OR_READ /////DOUBT
			      Paddr_temp=Haddr2;
				  Pwrite_temp=Hwrite;
				  Pselx_temp=tempselx;
				  Pwdata_temp=Hwdata;
				  Penable_temp=0;
				  Hreadyout_temp=0;		   
			     end
		        end

	ST_WENABLE :begin
	             if (~valid && Hwritereg) 
			      begin:WENABLE_TO_IDLE
				   Pselx_temp=0;
				   Penable_temp=0;
				   Hreadyout_temp=0;
				  end

			  
			    else 
			     begin:WENABLE_TO_WAIT_OR_READ /////DOUBT
				  Pselx_temp=0;
				  Penable_temp=0;
				  Hreadyout_temp=0;		   
			     end

		        end

 endcase
end


////////////OUTPUT LOGIC:SEQUENTIAL

always @(posedge Hclk)
 begin
  
  if (~Hresetn)
   begin
    Paddr<=0;
	Pwrite<=0;
	Pselx<=0;
	Pwdata<=0;
	Penable<=0;
	Hreadyout<=0;
   end
  
  else
   begin
        Paddr<=Paddr_temp;
	Pwrite<=Pwrite_temp;
	Pselx<=Pselx_temp;
	Pwdata<=Pwdata_temp;
	Penable<=Penable_temp;
	Hreadyout<=Hreadyout_temp;
   end
 end

endmodule

AHB2APB_Brdg_MS5_UVM/rtl/AHB_Slave_Interface.sv

module AHB_Slave_Interface(Hclk,Hresetn,Hwrite,Hreadyin,Htrans,Haddr,Hwdata,
			   Prdata,valid,Haddr1,Haddr2,Hwdata1,Hwdata2,Hrdata,Hwritereg,tempselx,Hresp);
input Hclk,Hresetn;
input Hwrite,Hreadyin;
input [1:0] Htrans;
input [31:0] Haddr,Hwdata,Prdata;
output reg valid;
output reg [31:0] Haddr1,Haddr2,Hwdata1,Hwdata2;
output [31:0] Hrdata; 
output reg Hwritereg;
output reg [2:0] tempselx;
output  [1:0] Hresp;



/// Implementing Pipeline Logic for Address,Data and Control Signal

	always @(posedge Hclk)
		begin
		
			if (~Hresetn)
				begin
					Haddr1<=0;
					Haddr2<=0;
				end
			else
				begin
					Haddr1<=Haddr;
					Haddr2<=Haddr1;
				end
		
		end

	always @(posedge Hclk)
		begin
		
			if (~Hresetn)
				begin
					Hwdata1<=0;
					Hwdata2<=0;
				end
			else
				begin
					Hwdata1<=Hwdata;
					Hwdata2<=Hwdata1;
				end
		
		end
		
	always @(posedge Hclk)
		begin	
			if (~Hresetn)
				Hwritereg<=0;
			else
				Hwritereg<=Hwrite;
		end
		
		
/// Implementing Valid Logic Generation

	always @(Hreadyin,Haddr,Htrans,Hresetn)
		begin
			valid=0;
			if (Hresetn && Hreadyin && (Haddr>=32'h8000_0000 && Haddr<32'h8C00_0000) && (Htrans==2'b10 || Htrans==2'b11) )
				valid=1;

		end
		
/// Implementing Tempselx Logic

	always @(Haddr,Hresetn)
		begin
			tempselx=3'b000;
			if (Hresetn && Haddr>=32'h8000_0000 && Haddr<32'h8400_0000) begin
				tempselx=3'b001;
				
			end
			else if (Hresetn && Haddr>=32'h8400_0000 && Haddr<32'h8800_0000)
				tempselx=3'b010;
			else if (Hresetn && Haddr>=32'h8800_0000 && Haddr<32'h8C00_0000)
				tempselx=3'b100;
			`ifdef BUG_Slave_Err
					tempselx = 3'bxxx;
			`endif
		end
	

assign Hrdata = Prdata;
assign Hresp = (tempselx == 3'b000) ? 2'b01 : 2'b00;

endmodule

AHB2APB_Brdg_MS2_Class/rtl/Bridge_Top.sv
// Bridge Top

module Bridge_Top(Hclk,Pclk,Hresetn,Hwrite,Hreadyin,Hreadyout,Hwdata,Haddr,Htrans,Prdata,Penable,Pwrite,Pselx,Paddr,Pwdata,Hresp,Hrdata);

input Hclk,Pclk,Hresetn,Hwrite,Hreadyin;
input [31:0] Hwdata,Haddr;
input [31:0] Prdata;
input[1:0] Htrans;
output Penable,Pwrite,Hreadyout;
output [1:0] Hresp; 
output [2:0] Pselx;
output [31:0] Paddr,Pwdata;
output [31:0] Hrdata;

//////////INTERMEDIATE SIGNALS - HCLK DOMAIN

wire valid;
wire [31:0] Haddr1,Haddr2,Hwdata1,Hwdata2;
wire Hwritereg;
wire [2:0] tempselx;
wire [31:0] Prdata_hclk;

// APB signals in HCLK domain (before CDC)
wire Penable_hclk, Pwrite_hclk;
wire [2:0] Pselx_hclk;
wire [31:0] Paddr_hclk, Pwdata_hclk;

//////////MODULE INSTANTIATIONS

// AHB Slave Interface - runs on HCLK
AHB_Slave_Interface AHBSlave (
    .Hclk(Hclk),
    .Hresetn(Hresetn),
    .Hwrite(Hwrite),
    .Hreadyin(Hreadyin),
    .Htrans(Htrans),
    .Haddr(Haddr),
    .Hwdata(Hwdata),
    .Prdata(Prdata_hclk),
    .valid(valid),
    .Haddr1(Haddr1),
    .Haddr2(Haddr2),
    .Hwdata1(Hwdata1),
    .Hwdata2(Hwdata2),
    .Hrdata(Hrdata),
    .Hwritereg(Hwritereg),
    .tempselx(tempselx),
    .Hresp(Hresp)
);

// APB FSM Controller - runs on HCLK (NOT Pclk!)
APB_FSM_Controller APBControl (
    .Hclk(Hclk),
    .Hresetn(Hresetn),
    .valid(valid),
    .Haddr(Haddr),
    .Haddr1(Haddr1),
    .Haddr2(Haddr2),
    .Hwdata(Hwdata),
    .Hwdata1(Hwdata1),
    .Hwdata2(Hwdata2),
    .Prdata(Prdata_hclk),
    .Hwrite(Hwrite),
    .Hwritereg(Hwritereg),
    .tempselx(tempselx),
    .Pwrite(Pwrite_hclk),
    .Penable(Penable_hclk),
    .Pselx(Pselx_hclk),
    .Paddr(Paddr_hclk),
    .Pwdata(Pwdata_hclk),
    .Hreadyout(Hreadyout)
);

// CDC Handler - synchronizes APB signals between HCLK and PCLK domains
CDC_Handler CDC (
    .Hclk(Hclk),
    .Pclk(Pclk),
    .Hresetn(Hresetn),
    // APB outputs from FSM (HCLK domain)
    .Penable_hclk(Penable_hclk),
    .Pwrite_hclk(Pwrite_hclk),
    .Pselx_hclk(Pselx_hclk),
    .Paddr_hclk(Paddr_hclk),
    .Pwdata_hclk(Pwdata_hclk),
    // APB outputs to APB bus (PCLK domain)
    .Penable_pclk(Penable),
    .Pwrite_pclk(Pwrite),
    .Pselx_pclk(Pselx),
    .Paddr_pclk(Paddr),
    .Pwdata_pclk(Pwdata),
    // APB read data path
    .Prdata_pclk(Prdata),
    .Prdata_hclk(Prdata_hclk)
);

endmodule

tb_sanity_check.sv
`timescale 1ns/1ps

module tb_sanity_check;
  // Clock signals
  reg        Hclk;
  reg        Pclk;
  
  // AHB-lite signals
  reg        Hresetn;
  reg        Hwrite;
  reg        Hreadyin;
  reg [1:0]  Htrans;
  reg [31:0] Hwdata;
  reg [31:0] Haddr;
  reg [31:0] Prdata;

  //APB signals
  wire       Penable;
  wire       Pwrite;
  wire       Hreadyout;
  wire [1:0] Hresp;
  wire [2:0] Pselx;
  wire [31:0] Paddr;
  wire [31:0] Pwdata;
  wire [31:0] Hrdata;

  // DUT
  Bridge_Top dut (
    .Hclk(Hclk),
    .Pclk(Pclk),
    .Hresetn(Hresetn),
    .Hwrite(Hwrite),
    .Hreadyin(Hreadyin),
    .Hreadyout(Hreadyout),
    .Hwdata(Hwdata),
    .Haddr(Haddr),
    .Htrans(Htrans),
    .Prdata(Prdata),
    .Penable(Penable),
    .Pwrite(Pwrite),
    .Pselx(Pselx),
    .Paddr(Paddr),
    .Pwdata(Pwdata),
    .Hresp(Hresp),
    .Hrdata(Hrdata)
  );

  // Clock generation
  // HCLK: 10ns period (100MHz)
  always #5 Hclk = ~Hclk;
  
  // PCLK: 30ns period (33.3MHz) - 3x slower than HCLK
  always #10 Pclk = ~Pclk;

  initial begin
    $dumpfile("waveforms/tb_sanity_check.vcd");
    $dumpvars(0, tb_sanity_check);
  end

  initial begin
    // init
    Hclk     = 1'b0;
    Pclk     = 1'b0;
    Hresetn  = 1'b0;
    Hwrite   = 1'b0;
    Hreadyin = 1'b1;
    Htrans   = 2'b00;
    Hwdata   = 32'h0;
    Haddr    = 32'h0;

    // reset deassert
    repeat (2) @(posedge Hclk);
    #1 Hresetn = 1'b1;

    // One AHB write transaction to valid APB slave 0 range
    wait (Hreadyout == 1'b1);
    @(posedge Hclk);
    #1;
    Hwrite   = 1'b1;
    Htrans   = 2'b10; // NONSEQ
    Haddr    = 32'h8000_0011; // addr1
    Hreadyin = 1'b1;

    wait (Hreadyout == 1'b1);
    @(posedge Hclk);
    #1;
    Htrans = 2'b10; // NONSEQ
    Hwdata = 32'h8000_0011; // data1
    Haddr    = 32'h8000_0022; // addr2

    wait (Hreadyout == 1'b1);
    @(posedge Hclk);
    #1;
    Htrans = 2'b10; // NONSEQ
    Hwdata = 32'h8000_0022; // data2
    Haddr    = 32'h8000_0033; // addr3

    wait (Hreadyout == 1'b1);
    @(posedge Hclk);
    #1;
    Htrans = 2'b10; // NONSEQ
    Hwdata = 32'h8000_0033; // data3
    Haddr    = 32'h8000_0044; // addr4

    wait (Hreadyout == 1'b1);
    @(posedge Hclk);
    #1;
    Htrans = 2'b10; // NONSEQ
    Hwdata = 32'h8000_0044; // data4
    Haddr    = 32'h8000_0055; // addr5

    wait (Hreadyout == 1'b1);
    @(posedge Hclk);
    #1;
    Htrans = 2'b00; // IDLE
    Hwdata = 32'hDEAD_DEAD;

    wait (Hreadyout == 1'b1);
    repeat (6) @(posedge Hclk);

    wait (Hreadyout == 1'b1);
    @(posedge Hclk);
    #1;
    Htrans = 2'b10; // NONSEQ
    Haddr    = 32'h8000_0050; // addr6
    wait (Hreadyout == 1'b1);
    @(posedge Hclk);
    #1;
    Hwdata = 32'h8000_0077; // data6
    
    wait (Hreadyout == 1'b1);
    @(posedge Hclk);
    #1;
    Htrans = 2'b11; // SEQ
    Haddr    = 32'h8000_0054; // addr7
    wait (Hreadyout == 1'b1);
    @(posedge Hclk);
    #1;
    Hwdata = 32'h8000_0088; // data7
        
    wait (Hreadyout == 1'b1);
    @(posedge Hclk);
    #1;
    Htrans = 2'b11; // SEQ
    Haddr    = 32'h8000_0058; // addr8
    wait (Hreadyout == 1'b1);
    @(posedge Hclk);
    #1;
    Hwdata = 32'h8000_0099; // data8
        
    wait (Hreadyout == 1'b1);
    @(posedge Hclk);
    #1;
    Htrans = 2'b11; // SEQ
    Haddr    = 32'h8000_005C; // addr9
    wait (Hreadyout == 1'b1);
    @(posedge Hclk);
    #1;
    Hwdata = 32'h8000_00AA; // data9
    
    // wait (Hreadyout == 1'b1);
    // @(posedge Hclk);
    // #1;
    // Htrans = 2'b00; // IDLE
    // Hwdata = 32'hDEAD_DEAD; // data10
    
    wait (Hreadyout == 1'b1);
    repeat (6) @(posedge Hclk);

    wait (Hreadyout == 1'b1);
    @(posedge Hclk);
    #1;
    Htrans = 2'b10; // NONSEQ
    Haddr    = 32'h8000_00AA; // addr11
    Hwrite   = 1'b0;
    wait (Paddr == Haddr && Pwrite == 1'b0);
    Prdata  = 32'h1234_5678; // read data

    // allow APB side to complete
    wait (Hreadyout == 1'b1);
    repeat (6) @(posedge Hclk);
    $finish;
  end

  // Simple observation
  always @(posedge Hclk) begin
    if (Pselx != 3'b000) begin
      $display("[%0t] APB sel=%b addr=%h write=%b enable=%b wdata=%h", $time, Pselx, Paddr, Pwrite, Penable, Pwdata);
    end
  end

endmodule

AHB2APB_Brdg_MS2_Class/tb_sanity_check.vcd
$date
	Wed Feb 18 12:02:22 2026
$end

$version
	Synopsys VCS version L-2016.06-SP2_Full64
$end

$timescale
	1ps
$end

$comment Csum: 1 d42e2f88a50b773b $end


$scope module tb_sanity_check $end
$var reg 1 ! Hclk $end
$var reg 1 " Pclk $end
$var reg 1 # Hresetn $end
$var reg 1 $ Hwrite $end
$var reg 1 % Hreadyin $end
$var reg 2 & Htrans [1:0] $end
$var reg 32 ' Hwdata [31:0] $end
$var reg 32 ( Haddr [31:0] $end
$var reg 32 ) Prdata [31:0] $end
$var wire 1 * Penable $end
$var wire 1 + Pwrite $end
$var wire 1 , Hreadyout $end
$var wire 2 - Hresp [1:0] $end
$var wire 3 . Pselx [2:0] $end
$var wire 32 / Paddr [31:0] $end
$var wire 32 0 Pwdata [31:0] $end
$var wire 32 1 Hrdata [31:0] $end

$scope module dut $end
$var wire 1 2 Hclk $end
$var wire 1 3 Pclk $end
$var wire 1 4 Hresetn $end
$var wire 1 5 Hwrite $end
$var wire 1 6 Hreadyin $end
$var wire 32 7 Hwdata [31:0] $end
$var wire 32 8 Haddr [31:0] $end
$var wire 32 9 Prdata [31:0] $end
$var wire 2 : Htrans [1:0] $end
$var wire 1 * Penable $end
$var wire 1 + Pwrite $end
$var wire 1 , Hreadyout $end
$var wire 2 - Hresp [1:0] $end
$var wire 3 . Pselx [2:0] $end
$var wire 32 / Paddr [31:0] $end
$var wire 32 0 Pwdata [31:0] $end
$var wire 32 1 Hrdata [31:0] $end
$var wire 1 ; valid $end
$var wire 32 < Haddr1 [31:0] $end
$var wire 32 = Haddr2 [31:0] $end
$var wire 32 > Hwdata1 [31:0] $end
$var wire 32 ? Hwdata2 [31:0] $end
$var wire 1 @ Hwritereg $end
$var wire 3 A tempselx [2:0] $end
$var wire 32 B Prdata_hclk [31:0] $end
$var wire 1 C Penable_hclk $end
$var wire 1 D Pwrite_hclk $end
$var wire 3 E Pselx_hclk [2:0] $end
$var wire 32 F Paddr_hclk [31:0] $end
$var wire 32 G Pwdata_hclk [31:0] $end

$scope module AHBSlave $end
$var wire 1 2 Hclk $end
$var wire 1 4 Hresetn $end
$var wire 1 5 Hwrite $end
$var wire 1 6 Hreadyin $end
$var wire 2 : Htrans [1:0] $end
$var wire 32 8 Haddr [31:0] $end
$var wire 32 7 Hwdata [31:0] $end
$var wire 32 B Prdata [31:0] $end
$var reg 1 H valid $end
$var reg 32 I Haddr1 [31:0] $end
$var reg 32 J Haddr2 [31:0] $end
$var reg 32 K Hwdata1 [31:0] $end
$var reg 32 L Hwdata2 [31:0] $end
$var wire 32 1 Hrdata [31:0] $end
$var reg 1 M Hwritereg $end
$var reg 3 N tempselx [2:0] $end
$var wire 2 - Hresp [1:0] $end
$upscope $end


$scope module APBControl $end
$var wire 1 2 Hclk $end
$var wire 1 4 Hresetn $end
$var wire 1 ; valid $end
$var wire 1 5 Hwrite $end
$var wire 1 @ Hwritereg $end
$var wire 32 7 Hwdata [31:0] $end
$var wire 32 8 Haddr [31:0] $end
$var wire 32 < Haddr1 [31:0] $end
$var wire 32 = Haddr2 [31:0] $end
$var wire 32 > Hwdata1 [31:0] $end
$var wire 32 ? Hwdata2 [31:0] $end
$var wire 32 B Prdata [31:0] $end
$var wire 3 A tempselx [2:0] $end
$var reg 1 O Pwrite $end
$var reg 1 P Penable $end
$var reg 1 Q Hreadyout $end
$var reg 3 R Pselx [2:0] $end
$var reg 32 S Paddr [31:0] $end
$var reg 32 T Pwdata [31:0] $end
$var reg 3 U PRESENT_STATE [2:0] $end
$var reg 3 V NEXT_STATE [2:0] $end
$var reg 1 W Penable_temp $end
$var reg 1 X Hreadyout_temp $end
$var reg 1 Y Pwrite_temp $end
$var reg 3 Z Pselx_temp [2:0] $end
$var reg 32 [ Paddr_temp [31:0] $end
$var reg 32 \ Pwdata_temp [31:0] $end

$scope begin PRESENT_STATE_LOGIC $end
$upscope $end


$scope begin NEXT_STATE_LOGIC $end
$upscope $end


$scope begin OUTPUT_COMBINATIONAL_LOGIC $end

$scope begin IDLE_TO_READ $end
$upscope $end


$scope begin IDLE_TO_WWAIT $end
$upscope $end


$scope begin IDLE_TO_IDLE $end
$upscope $end


$scope begin WAIT_TO_WRITE $end
$upscope $end


$scope begin WAIT_TO_WRITEP $end
$upscope $end


$scope begin READ_TO_RENABLE $end
$upscope $end


$scope begin WRITE_TO_WENABLE $end
$upscope $end


$scope begin WRITE_TO_WENABLEP $end
$upscope $end


$scope begin WRITEP_TO_WENABLEP $end
$upscope $end


$scope begin RENABLE_TO_READ $end
$upscope $end


$scope begin RENABLE_TO_WWAIT $end
$upscope $end


$scope begin RENABLE_TO_IDLE $end
$upscope $end


$scope begin WENABLEP_TO_WRITEP $end
$upscope $end


$scope begin WENABLEP_TO_WRITE_OR_READ $end
$upscope $end


$scope begin WENABLE_TO_IDLE $end
$upscope $end


$scope begin WENABLE_TO_WAIT_OR_READ $end
$upscope $end

$upscope $end

$upscope $end


$scope module CDC $end
$var wire 1 2 Hclk $end
$var wire 1 3 Pclk $end
$var wire 1 4 Hresetn $end
$var wire 1 C Penable_hclk $end
$var wire 1 D Pwrite_hclk $end
$var wire 3 E Pselx_hclk [2:0] $end
$var wire 32 F Paddr_hclk [31:0] $end
$var wire 32 G Pwdata_hclk [31:0] $end
$var wire 1 * Penable_pclk $end
$var wire 1 + Pwrite_pclk $end
$var wire 3 . Pselx_pclk [2:0] $end
$var wire 32 / Paddr_pclk [31:0] $end
$var wire 32 0 Pwdata_pclk [31:0] $end
$var wire 32 9 Prdata_pclk [31:0] $end
$var wire 32 B Prdata_hclk [31:0] $end
$var reg 1 ] Penable_sync1 $end
$var reg 1 ^ Penable_sync2 $end
$var reg 1 _ Pwrite_sync1 $end
$var reg 1 ` Pwrite_sync2 $end
$var reg 3 a Pselx_sync1 [2:0] $end
$var reg 3 b Pselx_sync2 [2:0] $end
$var reg 32 c Paddr_sync1 [31:0] $end
$var reg 32 d Paddr_sync2 [31:0] $end
$var reg 32 e Pwdata_sync1 [31:0] $end
$var reg 32 f Pwdata_sync2 [31:0] $end
$var reg 32 g Prdata_sync1 [31:0] $end
$var reg 32 h Prdata_sync2 [31:0] $end
$upscope $end

$upscope $end

$upscope $end

$enddefinitions $end

#0
$dumpvars
xM
0H
xQ
xP
xO
0!
1%
x,
xX
0#
0$
x@
0"
x*
xC
x]
x^
xW
x+
xD
x_
x`
xY
16
04
05
0;
bxxxxxxxxxxxxxxxxxxxxxxxxxxxxxxxx I
bxxxxxxxxxxxxxxxxxxxxxxxxxxxxxxxx J
bxxxxxxxxxxxxxxxxxxxxxxxxxxxxxxxx K
bxxxxxxxxxxxxxxxxxxxxxxxxxxxxxxxx L
b000 N
bxxxxxxxxxxxxxxxxxxxxxxxxxxxxxxxx S
bxxx R
bxxxxxxxxxxxxxxxxxxxxxxxxxxxxxxxx T
b00000000000000000000000000000000 (
bxxxxxxxxxxxxxxxxxxxxxxxxxxxxxxxx <
bxxxxxxxxxxxxxxxxxxxxxxxxxxxxxxxx =
bxxxxxxxxxxxxxxxxxxxxxxxxxxxxxxxx 1
b00 -
b00 &
b00000000000000000000000000000000 '
bxxxxxxxxxxxxxxxxxxxxxxxxxxxxxxxx >
bxxxxxxxxxxxxxxxxxxxxxxxxxxxxxxxx ?
b000 V
bxxx U
bxxxxxxxxxxxxxxxxxxxxxxxxxxxxxxxx /
bxxxxxxxxxxxxxxxxxxxxxxxxxxxxxxxx F
bxxxxxxxxxxxxxxxxxxxxxxxxxxxxxxxx c
bxxxxxxxxxxxxxxxxxxxxxxxxxxxxxxxx d
bxxxxxxxxxxxxxxxxxxxxxxxxxxxxxxxx [
bxxxxxxxxxxxxxxxxxxxxxxxxxxxxxxxx )
bxxxxxxxxxxxxxxxxxxxxxxxxxxxxxxxx B
bxxxxxxxxxxxxxxxxxxxxxxxxxxxxxxxx g
bxxxxxxxxxxxxxxxxxxxxxxxxxxxxxxxx h
bxxx .
bxxx E
bxxx a
bxxx b
bxxx Z
bxxxxxxxxxxxxxxxxxxxxxxxxxxxxxxxx 0
bxxxxxxxxxxxxxxxxxxxxxxxxxxxxxxxx G
bxxxxxxxxxxxxxxxxxxxxxxxxxxxxxxxx e
bxxxxxxxxxxxxxxxxxxxxxxxxxxxxxxxx f
bxxxxxxxxxxxxxxxxxxxxxxxxxxxxxxxx \
b00000000000000000000000000000000 8
b00 :
b00000000000000000000000000000000 7
bxxxxxxxxxxxxxxxxxxxxxxxxxxxxxxxx 9
b000 A
02
03
$end
#5000
1!
12
b00000000000000000000000000000000 I
b00000000000000000000000000000000 <
b00000000000000000000000000000000 J
b00000000000000000000000000000000 =
b00000000000000000000000000000000 K
b00000000000000000000000000000000 >
b00000000000000000000000000000000 L
b00000000000000000000000000000000 ?
0M
0@
b000 U
b00000000000000000000000000000000 S
b00000000000000000000000000000000 F
0O
0D
b000 R
b000 E
b00000000000000000000000000000000 T
b00000000000000000000000000000000 G
0P
0C
0Q
0,
b00000000000000000000000000000000 g
b00000000000000000000000000000000 h
b00000000000000000000000000000000 B
b00000000000000000000000000000000 1
1X
0W
b000 Z
#10000
1"
13
0!
02
0]
0_
b000 a
b00000000000000000000000000000000 c
b00000000000000000000000000000000 e
0^
0*
0`
0+
b000 b
b000 .
b00000000000000000000000000000000 d
b00000000000000000000000000000000 /
b00000000000000000000000000000000 f
b00000000000000000000000000000000 0
#15000
1!
12
#16000
1#
14
#20000
0"
03
0!
02
#25000
1!
12
bxxxxxxxxxxxxxxxxxxxxxxxxxxxxxxxx S
bxxxxxxxxxxxxxxxxxxxxxxxxxxxxxxxx F
xO
xD
bxxxxxxxxxxxxxxxxxxxxxxxxxxxxxxxx T
bxxxxxxxxxxxxxxxxxxxxxxxxxxxxxxxx G
1Q
1,
bxxxxxxxxxxxxxxxxxxxxxxxxxxxxxxxx g
#30000
1"
13
0!
02
x_
bxxxxxxxxxxxxxxxxxxxxxxxxxxxxxxxx c
bxxxxxxxxxxxxxxxxxxxxxxxxxxxxxxxx e
#35000
1!
12
bxxxxxxxxxxxxxxxxxxxxxxxxxxxxxxxx h
bxxxxxxxxxxxxxxxxxxxxxxxxxxxxxxxx B
bxxxxxxxxxxxxxxxxxxxxxxxxxxxxxxxx 1
#36000
1$
15
b10 &
b10 :
b10000000000000000000000001010100 (
b10000000000000000000000001010100 8
1H
1;
b001 N
b001 A
b001 V
#40000
0"
03
0!
02
